Workbook

Sheet Project Overview
A1: MapleLeaf Financial Planning Inc.
A3: Retirement Readiness Analysis
A5: Company Overview
B6: MapleLeaf Financial Planning Inc. helps people plan for retirement. The company gives simple financial advice and helps clients reach their money goals.
A7: Project Purpose
B8: This workbook shows how long it may take for a client to reach a retirement savings goal.
A9: What This File Does
B10: Calculates years needed to reach a target fund.
B11: Shows the effect of monthly investments.
B12: Uses an expected annual return rate.
B13: Helps compare retirement plans.
A14: Users
B15: Financial Advisors, Wealth Managers, and Planning Analysts.
A16: Workbook Sheets
B17: Project Overview, Retirement Calculator, Growth Projection, and Dashboard.

Sheet Retirement Calculator
A1: Retirement Calculator
A3: Input | B3: Value | D3: Result | E3: Value
A4: Current Investment Portfolio | B4: 35000 | D4: Estimated Years to Goal | E4: =NPER(B6/12,-B5,-B4,B7)/12 -> 22.38535
A5: Monthly Investment Plan | B5: 650 | D5: Estimated Retirement Age | E5: =B8+E4 -> 57.38535
A6: Expected Portfolio Return | B6: 0.06 | D6: Total Contributions | E6: =B5*12*E4 -> 174605.73
A7: Retirement Target Fund | B7: 500000 | D7: Estimated Investment Growth | E7: =B7-B4-E6 -> 290394.27
A8: Current Age | B8: 35 | D8: Status | E8: =IF(E4<=25,"On Track","Needs Review") -> On Track

Sheet Growth Projection
A1: Growth Projection
A3: Year | B3: Age | C3: Start Balance | D3: Annual Contribution | E3: End Balance
A4: 0 | B4: ='Retirement Calculator'!B8+A4 -> 35 | C4: ='Retirement Calculator'!B4 -> 35000 | D4: ='Retirement Calculator'!B5*12 -> 7800 | E4: =C4*(1+'Retirement Calculator'!B6)+D4 -> 44900
A5: 1 | B5: ='Retirement Calculator'!B9+A5 -> 1 | C5: =E4 -> 44900 | D5: ='Retirement Calculator'!B6*12 -> 0.72 | E5: =C5*(1+'Retirement Calculator'!B7)+D5 -> 2.2450045e+10
A6: 2 | B6: ='Retirement Calculator'!B10+A6 -> 2 | C6: =E5 -> 2.2450045e+10 | D6: ='Retirement Calculator'!B7*12 -> 6000000 | E6: =C6*(1+'Retirement Calculator'!B8)+D6 -> 8.0820762e+11
A7: 3 | B7: ='Retirement Calculator'!B11+A7 -> 3 | C7: =E6 -> 8.0820762e+11 | D7: ='Retirement Calculator'!B8*12 -> 420 | E7: =C7*(1+'Retirement Calculator'!B9)+D7 -> 8.0820762e+11
A8: 4 | B8: ='Retirement Calculator'!B12+A8 -> 4 | C8: =E7 -> 8.0820762e+11 | D8: ='Retirement Calculator'!B9*12 -> 0 | E8: =C8*(1+'Retirement Calculator'!B10)+D8 -> 8.0820762e+11
A9: 5 | B9: ='Retirement Calculator'!B13+A9 -> 5 | C9: =E8 -> 8.0820762e+11 | D9: ='Retirement Calculator'!B10*12 -> 0 | E9: =C9*(1+'Retirement Calculator'!B11)+D9 -> 8.0820762e+11
A10: 6 | B10: ='Retirement Calculator'!B14+A10 -> 6 | C10: =E9 -> 8.0820762e+11 | D10: ='Retirement Calculator'!B11*12 -> 0 | E10: =C10*(1+'Retirement Calculator'!B12)+D10 -> 8.0820762e+11
A11: 7 | B11: ='Retirement Calculator'!B15+A11 -> 7 | C11: =E10 -> 8.0820762e+11 | D11: ='Retirement Calculator'!B12*12 -> 0 | E11: =C11*(1+'Retirement Calculator'!B13)+D11 -> 8.0820762e+11
A12: 8 | B12: ='Retirement Calculator'!B16+A12 -> 8 | C12: =E11 -> 8.0820762e+11 | D12: ='Retirement Calculator'!B13*12 -> 0 | E12: =C12*(1+'Retirement Calculator'!B14)+D12 -> 8.0820762e+11
A13: 9 | B13: ='Retirement Calculator'!B17+A13 -> 9 | C13: =E12 -> 8.0820762e+11 | D13: ='Retirement Calculator'!B14*12 -> 0 | E13: =C13*(1+'Retirement Calculator'!B15)+D13 -> 8.0820762e+11
A14: 10 | B14: ='Retirement Calculator'!B18+A14 -> 10 | C14: =E13 -> 8.0820762e+11 | D14: ='Retirement Calculator'!B15*12 -> 0 | E14: =C14*(1+'Retirement Calculator'!B16)+D14 -> 8.0820762e+11
A15: 11 | B15: ='Retirement Calculator'!B19+A15 -> 11 | C15: =E14 -> 8.0820762e+11 | D15: ='Retirement Calculator'!B16*12 -> 0 | E15: =C15*(1+'Retirement Calculator'!B17)+D15 -> 8.0820762e+11
A16: 12 | B16: ='Retirement Calculator'!B20+A16 -> 12 | C16: =E15 -> 8.0820762e+11 | D16: ='Retirement Calculator'!B17*12 -> 0 | E16: =C16*(1+'Retirement Calculator'!B18)+D16 -> 8.0820762e+11
... A34: 30 | B34: ='Retirement Calculator'!B38+A34 -> 30 | C34: =E33 -> 8.0820762e+11 | D34: ='Retirement Calculator'!B35*12 -> 0 | E34: =C34*(1+'Retirement Calculator'!B36)+D34 -> 8.0820762e+11

Sheet Dashboard
A1: Retirement Dashboard
A3: Metric | B3: Value
A4: Target Fund | B4: ='Retirement Calculator'!B7 -> 500000
A5: Years to Goal | B5: ='Retirement Calculator'!E4 -> 22.38535
A6: Retirement Age | B6: ='Retirement Calculator'!E5 -> 57.38535
