Workbook

Sheet README
A1: Month-End Close Reconciliation & AP/AR Risk Dashboard
A3: Section | B3: Simple explanation | C3: Why it matters
A4: Project goal | B4: This Excel file helps a finance team check month-end data. It compares ERP transactions with bank transactions. It also shows unpaid invoices. | C4: Companies need this work every month. It saves time and finds errors.
A5: Business problem | B5: Many companies have many AP, AR, and bank records. Some records do not match. Some invoices are old. This can make month-end close slow. | C5: A manager wants clean data, clear exceptions, and fast reports.
A6: What this workbook does | B6: It imports sample ERP data, sample bank data, and sample invoice data. It checks matches, amount differences, date differences, and invoice risk. | C6: It shows practical Excel and finance skills.
A7: How to use it | B7: Start with the Dashboard sheet. Then check Reconciliation for transaction problems. Check Open_Invoices for AP and AR risk. | C7: This is how a real accounting team would use the file.
A8: Main result | B8: The dashboard shows matched transactions, unmatched ERP items, bank-only items, old invoices, and high-risk items. | C8: This helps the team know what to fix first.
A9: Sheet: Mapping_Rules | B9: This sheet has the rules. For example, how much amount difference is allowed and how many days difference is okay. | C9: Rules make the file easy to change.
A10: Sheet: ERP_Transactions | B10: This sheet has sample ERP transactions from AP, AR, GL, Payroll, and bank fees. | C10: This is the main accounting system data.
A11: Sheet: Bank_Statement | B11: This sheet has sample bank records. Some records match ERP. Some records do not match. | C11: This helps test bank reconciliation.
A12: Sheet: Reconciliation | B12: This sheet compares ERP with bank data by reference number. It shows matched items and review items. | C12: This is a key month-end close task.
A13: Sheet: Open_Invoices | B13: This sheet shows unpaid AP and AR invoices. It calculates open amount, days overdue, aging bucket, and risk level. | C13: This helps cash collection and vendor payment planning.
A14: Sheet: Analysis_Model | B14: This sheet has summary formulas. It works like a simple data model. | C14: It supports the dashboard.
... A21: GitHub note | B21: Upload the workbook with screenshots. Add a short README. Explain the business problem, the Excel skills, and the result. | C21: This makes the portfolio easy to understand.

Sheet Mapping_Rules
A1: Mapping Rules and Control Inputs
A3: Control | B3: Value | C3: Explanation | E3: Modules | F3: Invoice Type | G3: Status | H3: Priority | I3: Exception Type | J3: Aging Bucket | K3: Owners | L3: Risk Level
A4: Amount tolerance | B4: 10 | C4: Amount difference allowed for automatic match | E4: AP | F4: AP | G4: Open | H4: High | I4: Missing from bank | J4: Current | K4: AP Clerk | L4: Normal
A5: Date tolerance days | B5: 3 | C5: Date difference allowed for automatic match | E5: AR | F5: AR | G5: Part Paid | H5: Medium | I5: Amount variance | J5: 1-30 | K5: AR Clerk | L5: Monitor
A6: Close date | B6: 46053 | C6: Month-end close date | E6: GL | G6: Disputed | H6: Low | I6: Date variance | J6: 31-60 | K6: Accounting Technician | L6: High Risk
A7: High risk amount | B7: 5000 | C7: Invoice amount above this value is high risk | E7: Payroll | G7: Promise to Pay | I7: Bank-only item | J7: 61-90 | K7: Finance Analyst | L7: Closed
A8: High risk days | B8: 60 | C8: Invoice days overdue above this value is high risk | E8: Bank Fees | G8: Closed | I8: Invoice risk | J8: 90+

Sheet ERP_Transactions
A1: ERP Transactions - Sample Data
A3: Txn_ID | B3: Txn_Date | C3: Period | D3: Module | E3: Vendor_Customer | F3: Description | G3: Reference_No | H3: Debit | I3: Credit | J3: Net_Amount | K3: Payment_Method | L3: Cost_Center | M3: GL_Account
A4: ERP-00001 | B4: 46043 | C4: 2026-01 | D4: AP | E4: Staples Canada | F4: Vendor payment - Staples Canada | G4: REF-100001 | H4: 0 | I4: 1763.18 | J4: -1763.18 | K4: Cheque | L4: 200-Sales | M4: 2000 AP
A5: ERP-00002 | B5: 46024 | C5: 2026-01 | D5: AP | E5: North Shore Telecom | F5: Vendor payment - North Shore Telecom | G5: REF-100002 | H5: 0 | I5: 1503.88 | J5: -1503.88 | K5: PAD | L5: 100-Admin | M5: 2000 AP
A6: ERP-00003 | B6: 46041 | C6: 2026-01 | D6: AP | E6: Vancouver Courier | F6: Vendor payment - Vancouver Courier | G6: REF-100003 | H6: 0 | I6: 119.77 | J6: -119.77 | K6: Cheque | L6: 400-Finance | M6: 2000 AP
A7: ERP-00004 | B7: 46047 | C7: 2026-01 | D7: AP | E7: Pacific Office Supplies | F7: Vendor payment - Pacific Office Supplies | G7: REF-100004 | H7: 0 | I7: 2405.16 | J7: -2405.16 | K7: Credit Card | L7: 300-Ops | M7: 2000 AP
A8: ERP-00005 | B8: 46040 | C8: 2026-01 | D8: AP | E8: BC Hydro | F8: Vendor payment - BC Hydro | G8: REF-100005 | H8: 0 | I8: 562.26 | J8: -562.26 | K8: Credit Card | L8: 500-IT | M8: 2000 AP
A9: ERP-00006 | B9: 46034 | C9: 2026-01 | D9: AR | E9: Harbour Design Co. | F9: Customer payment - Harbour Design Co. | G9: REF-100006 | H9: 730.79 | I9: 0 | J9: 730.79 | K9: Cheque | L9: 300-Ops | M9: 1200 AR
A10: ERP-00007 | B10: 46050 | C10: 2026-01 | D10: AP | E10: Pacific Office Supplies | F10: Vendor payment - Pacific Office Supplies | G10: REF-100007 | H10: 0 | I10: 2406.37 | J10: -2406.37 | K10: Wire | L10: 300-Ops | M10: 2000 AP
A11: ERP-00008 | B11: 46031 | C11: 2026-01 | D11: GL | E11: Granville Medical | F11: Manual GL entry | G11: REF-100008 | H11: 0 | I11: 3257.78 | J11: -3257.78 | K11: PAD | L11: 200-Sales | M11: 2000 AP
A12: ERP-00009 | B12: 46052 | C12: 2026-01 | D12: AR | E12: West Van Fitness | F12: Customer payment - West Van Fitness | G12: REF-100009 | H12: 1983.79 | I12: 0 | J12: 1983.79 | K12: Credit Card | L12: 100-Admin | M12: 1200 AR
A13: ERP-00010 | B13: 46035 | C13: 2026-01 | D13: AP | E13: North Shore Telecom | F13: Vendor payment - North Shore Telecom | G13: REF-100010 | H13: 0 | I13: 5668.39 | J13: -5668.39 | K13: PAD | L13: 300-Ops | M13: 2000 AP
A14: ERP-00011 | B14: 46052 | C14: 2026-01 | D14: AR | E14: Coastline Foods | F14: Customer payment - Coastline Foods | G14: REF-100011 | H14: 2361.75 | I14: 0 | J14: 2361.75 | K14: Cheque | L14: 500-IT | M14: 1200 AR
A15: ERP-00012 | B15: 46035 | C15: 2026-01 | D15: AR | E15: Coastline Foods | F15: Customer payment - Coastline Foods | G15: REF-100012 | H15: 4404.54 | I15: 0 | J15: 4404.54 | K15: EFT | L15: 100-Admin | M15: 1200 AR
... A503: ERP-00500 | B503: 46032 | C503: 2026-01 | D503: GL | E503: Maple Retail Group | F503: Manual GL entry | G503: REF-100500 | H503: 0 | I503: 1938 | J503: -1938 | K503: Wire | L503: 200-Sales | M503: 1010 Cash

Sheet Bank_Statement
A1: Bank Statement - Sample Data
A3: Bank_ID | B3: Bank_Date | C3: Bank_Description | D3: Reference_No | E3: Deposit | F3: Withdrawal | G3: Bank_Net | H3: Bank_Status
A4: BANK-1301 | B4: 46021 | C4: Payment to Metro Cleaning Ltd. | D4: REF-100366 | E4: 0 | F4: 3971.96 | G4: -3971.96 | H4: Imported
A5: BANK-1002 | B5: 46022 | C5: Payment to North Shore Telecom | D5: REF-100002 | E5: 0 | F5: 1503.88 | G5: -1503.88 | H5: Imported
A6: BANK-1098 | B6: 46022 | C6: Payment to Pacific Office Supplies | D6: REF-100115 | E6: 0 | F6: 1875.41 | G6: -1875.41 | H6: Imported
A7: BANK-1132 | B7: 46022 | C7: Deposit from Granville Medical | D7: REF-100158 | E7: 7841.71 | F7: 0 | G7: 7841.71 | H7: Imported
A8: BANK-1140 | B8: 46022 | C8: Deposit from Raincity Tech | D8: REF-100166 | E8: 790.7 | F8: 0 | G8: 790.7 | H8: Imported
A9: BANK-1231 | B9: 46022 | C9: Payment to Amazon Business | D9: REF-100283 | E9: 0 | F9: 2606.14 | G9: -2606.14 | H9: Imported
A10: BANK-1289 | B10: 46022 | C10: Monthly bank service charge | D10: REF-100351 | E10: 0 | F10: 114.1 | G10: -114.1 | H10: Imported
A11: BANK-1115 | B11: 46023 | C11: Payment to Pacific Office Supplies | D11: REF-100138 | E11: 0 | F11: 855.76 | G11: -855.76 | H11: Imported
A12: BANK-1147 | B12: 46023 | C12: Deposit from Coastline Foods | D12: REF-100175 | E12: 8092.26 | F12: 0 | G12: 8092.26 | H12: Imported
A13: BANK-1243 | B13: 46023 | C13: Payment to BC Hydro | D13: REF-100299 | E13: 0 | F13: 4848.51 | G13: -4848.51 | H13: Imported
A14: BANK-1328 | B14: 46023 | C14: Deposit from Maple Retail Group | D14: REF-100396 | E14: 6165.45 | F14: 0 | G14: 6165.45 | H14: Imported
A15: BANK-1341 | B15: 46023 | C15: Manual GL entry | D15: REF-100413 | E15: 0 | F15: 2958.5 | G15: -2958.5 | H15: Imported
... A448: BANK-1266 | B448: 46058 | C448: Deposit from Harbour Design Co. | D448: REF-100325 | E448: 4283 | F448: 0 | G448: 4283 | H448: Imported

Sheet Reconciliation
A1: Reconciliation - ERP vs Bank
A3: Txn_ID | B3: Txn_Date | C3: Module | D3: Vendor_Customer | E3: Reference_No | F3: ERP_Amount | G3: Bank_Amount | H3: Amount_Difference | I3: Bank_Date | J3: Date_Difference | K3: Reconciliation_Status | L3: Exception_Type | M3: Priority | N3: Suggested_Action | O3: GL_Account | P3: Owner | Q3: Reviewed? | R3: Review_Notes | S3: Days_To_Close
A4: ERP-00001 | B4: 46043 | C4: AP | D4: Staples Canada | E4: REF-100001 | F4: -1763.18 | G4: =IFERROR(XLOOKUP(E4,Bank_Statement!$D$4:$D$448,Bank_Statement!$G$4:$G$448,""),"") | H4: =IF(G4="","",F4-G4) | I4: =IFERROR(XLOOKUP(E4,Bank_Statement!$D$4:$D$448,Bank_Statement!$B$4:$B$448,""),"") | J4: =IF(I4="","",ABS(B4-I4)) | K4: =IF(G4="","Unmatched ERP",IF(AND(ABS(H4)<=Mapping_Rules!$B$4,ABS(J4)<=Mapping_Rules!$B$5),"Matched","Review")) | L4: =IF(K4="Matched","None",IF(G4="","Missing from bank",IF(ABS(H4)>Mapping_Rules!$B$4,"Amount variance","Date variance"))) | M4: =IF(K4="Matched","Low",IF(OR(IFERROR(ABS(H4),0)>Mapping_Rules!$B$7,IFERROR(J4,0)>Mapping_Rules!$B$8),"High","Medium")) | N4: =IF(K4="Matched","No action needed",IF(L4="Missing from bank","Check bank date or posting",IF(L4="Amount variance","Check invoice/payment amount","Check timing difference"))) | O4: 2000 AP | P4: AP Clerk | Q4: No | S4: =IF(K4="Matched",0,Mapping_Rules!$B$6-B4)
A5: ERP-00002 | B5: 46024 | C5: AP | D5: North Shore Telecom | E5: REF-100002 | F5: -1503.88 | G5: =IFERROR(XLOOKUP(E5,Bank_Statement!$D$4:$D$448,Bank_Statement!$G$4:$G$448,""),"") | H5: =IF(G5="","",F5-G5) | I5: =IFERROR(XLOOKUP(E5,Bank_Statement!$D$4:$D$448,Bank_Statement!$B$4:$B$448,""),"") | J5: =IF(I5="","",ABS(B5-I5)) | K5: =IF(G5="","Unmatched ERP",IF(AND(ABS(H5)<=Mapping_Rules!$B$4,ABS(J5)<=Mapping_Rules!$B$5),"Matched","Review")) | L5: =IF(K5="Matched","None",IF(G5="","Missing from bank",IF(ABS(H5)>Mapping_Rules!$B$4,"Amount variance","Date variance"))) | M5: =IF(K5="Matched","Low",IF(OR(IFERROR(ABS(H5),0)>Mapping_Rules!$B$7,IFERROR(J5,0)>Mapping_Rules!$B$8),"High","Medium")) | N5: =IF(K5="Matched","No action needed",IF(L5="Missing from bank","Check bank date or posting",IF(L5="Amount variance","Check invoice/payment amount","Check timing difference"))) | O5: 2000 AP | P5: AP Clerk | Q5: No | S5: =IF(K5="Matched",0,Mapping_Rules!$B$6-B5)
A6: ERP-00003 | B6: 46041 | C6: AP | D6: Vancouver Courier | E6: REF-100003 | F6: -119.77 | G6: =IFERROR(XLOOKUP(E6,Bank_Statement!$D$4:$D$448,Bank_Statement!$G$4:$G$448,""),"") | H6: =IF(G6="","",F6-G6) | I6: =IFERROR(XLOOKUP(E6,Bank_Statement!$D$4:$D$448,Bank_Statement!$B$4:$B$448,""),"") | J6: =IF(I6="","",ABS(B6-I6)) | K6: =IF(G6="","Unmatched ERP",IF(AND(ABS(H6)<=Mapping_Rules!$B$4,ABS(J6)<=Mapping_Rules!$B$5),"Matched","Review")) | L6: =IF(K6="Matched","None",IF(G6="","Missing from bank",IF(ABS(H6)>Mapping_Rules!$B$4,"Amount variance","Date variance"))) | M6: =IF(K6="Matched","Low",IF(OR(IFERROR(ABS(H6),0)>Mapping_Rules!$B$7,IFERROR(J6,0)>Mapping_Rules!$B$8),"High","Medium")) | N6: =IF(K6="Matched","No action needed",IF(L6="Missing from bank","Check bank date or posting",IF(L6="Amount variance","Check invoice/payment amount","Check timing difference"))) | O6: 2000 AP | P6: AP Clerk | Q6: No | S6: =IF(K6="Matched",0,Mapping_Rules!$B$6-B6)
A7: ERP-00004 | B7: 46047 | C7: AP | D7: Pacific Office Supplies | E7: REF-100004 | F7: -2405.16 | G7: =IFERROR(XLOOKUP(E7,Bank_Statement!$D$4:$D$448,Bank_Statement!$G$4:$G$448,""),"") | H7: =IF(G7="","",F7-G7) | I7: =IFERROR(XLOOKUP(E7,Bank_Statement!$D$4:$D$448,Bank_Statement!$B$4:$B$448,""),"") | J7: =IF(I7="","",ABS(B7-I7)) | K7: =IF(G7="","Unmatched ERP",IF(AND(ABS(H7)<=Mapping_Rules!$B$4,ABS(J7)<=Mapping_Rules!$B$5),"Matched","Review")) | L7: =IF(K7="Matched","None",IF(G7="","Missing from bank",IF(ABS(H7)>Mapping_Rules!$B$4,"Amount variance","Date variance"))) | M7: =IF(K7="Matched","Low",IF(OR(IFERROR(ABS(H7),0)>Mapping_Rules!$B$7,IFERROR(J7,0)>Mapping_Rules!$B$8),"High","Medium")) | N7: =IF(K7="Matched","No action needed",IF(L7="Missing from bank","Check bank date or posting",IF(L7="Amount variance","Check invoice/payment amount","Check timing difference"))) | O7: 2000 AP | P7: AP Clerk | Q7: No | S7: =IF(K7="Matched",0,Mapping_Rules!$B$6-B7)
A8: ERP-00005 | B8: 46040 | C8: AP | D8: BC Hydro | E8: REF-100005 | F8: -562.26 | G8: =IFERROR(XLOOKUP(E8,Bank_Statement!$D$4:$D$448,Bank_Statement!$G$4:$G$448,""),"") | H8: =IF(G8="","",F8-G8) | I8: =IFERROR(XLOOKUP(E8,Bank_Statement!$D$4:$D$448,Bank_Statement!$B$4:$B$448,""),"") | J8: =IF(I8="","",ABS(B8-I8)) | K8: =IF(G8="","Unmatched ERP",IF(AND(ABS(H8)<=Mapping_Rules!$B$4,ABS(J8)<=Mapping_Rules!$B$5),"Matched","Review")) | L8: =IF(K8="Matched","None",IF(G8="","Missing from bank",IF(ABS(H8)>Mapping_Rules!$B$4,"Amount variance","Date variance"))) | M8: =IF(K8="Matched","Low",IF(OR(IFERROR(ABS(H8),0)>Mapping_Rules!$B$7,IFERROR(J8,0)>Mapping_Rules!$B$8),"High","Medium")) | N8: =IF(K8="Matched","No action needed",IF(L8="Missing from bank","Check bank date or posting",IF(L8="Amount variance","Check invoice/payment amount","Check timing difference"))) | O8: 2000 AP | P8: AP Clerk | Q8: No | S8: =IF(K8="Matched",0,Mapping_Rules!$B$6-B8)
A9: ERP-00006 | B9: 46034 | C9: AR | D9: Harbour Design Co. | E9: REF-100006 | F9: 730.79 | G9: =IFERROR(XLOOKUP(E9,Bank_Statement!$D$4:$D$448,Bank_Statement!$G$4:$G$448,""),"") | H9: =IF(G9="","",F9-G9) | I9: =IFERROR(XLOOKUP(E9,Bank_Statement!$D$4:$D$448,Bank_Statement!$B$4:$B$448,""),"") | J9: =IF(I9="","",ABS(B9-I9)) | K9: =IF(G9="","Unmatched ERP",IF(AND(ABS(H9)<=Mapping_Rules!$B$4,ABS(J9)<=Mapping_Rules!$B$5),"Matched","Review")) | L9: =IF(K9="Matched","None",IF(G9="","Missing from bank",IF(ABS(H9)>Mapping_Rules!$B$4,"Amount variance","Date variance"))) | M9: =IF(K9="Matched","Low",IF(OR(IFERROR(ABS(H9),0)>Mapping_Rules!$B$7,IFERROR(J9,0)>Mapping_Rules!$B$8),"High","Medium")) | N9: =IF(K9="Matched","No action needed",IF(L9="Missing from bank","Check bank date or posting",IF(L9="Amount variance","Check invoice/payment amount","Check timing difference"))) | O9: 1200 AR | P9: AR Clerk | Q9: No | S9: =IF(K9="Matched",0,Mapping_Rules!$B$6-B9)
A10: ERP-00007 | B10: 46050 | C10: AP | D10: Pacific Office Supplies | E10: REF-100007 | F10: -2406.37 | G10: =IFERROR(XLOOKUP(E10,Bank_Statement!$D$4:$D$448,Bank_Statement!$G$4:$G$448,""),"") | H10: =IF(G10="","",F10-G10) | I10: =IFERROR(XLOOKUP(E10,Bank_Statement!$D$4:$D$448,Bank_Statement!$B$4:$B$448,""),"") | J10: =IF(I10="","",ABS(B10-I10)) | K10: =IF(G10="","Unmatched ERP",IF(AND(ABS(H10)<=Mapping_Rules!$B$4,ABS(J10)<=Mapping_Rules!$B$5),"Matched","Review")) | L10: =IF(K10="Matched","None",IF(G10="","Missing from bank",IF(ABS(H10)>Mapping_Rules!$B$4,"Amount variance","Date variance"))) | M10: =IF(K10="Matched","Low",IF(OR(IFERROR(ABS(H10),0)>Mapping_Rules!$B$7,IFERROR(J10,0)>Mapping_Rules!$B$8),"High","Medium")) | N10: =IF(K10="Matched","No action needed",IF(L10="Missing from bank","Check bank date or posting",IF(L10="Amount variance","Check invoice/payment amount","Check timing difference"))) | O10: 2000 AP | P10: AP Clerk | Q10: No | S10: =IF(K10="Matched",0,Mapping_Rules!$B$6-B10)
A11: ERP-00008 | B11: 46031 | C11: GL | D11: Granville Medical | E11: REF-100008 | F11: -3257.78 | G11: =IFERROR(XLOOKUP(E11,Bank_Statement!$D$4:$D$448,Bank_Statement!$G$4:$G$448,""),"") | H11: =IF(G11="","",F11-G11) | I11: =IFERROR(XLOOKUP(E11,Bank_Statement!$D$4:$D$448,Bank_Statement!$B$4:$B$448,""),"") | J11: =IF(I11="","",ABS(B11-I11)) | K11: =IF(G11="","Unmatched ERP",IF(AND(ABS(H11)<=Mapping_Rules!$B$4,ABS(J11)<=Mapping_Rules!$B$5),"Matched","Review")) | L11: =IF(K11="Matched","None",IF(G11="","Missing from bank",IF(ABS(H11)>Mapping_Rules!$B$4,"Amount variance","Date variance"))) | M11: =IF(K11="Matched","Low",IF(OR(IFERROR(ABS(H11),0)>Mapping_Rules!$B$7,IFERROR(J11,0)>Mapping_Rules!$B$8),"High","Medium")) | N11: =IF(K11="Matched","No action needed",IF(L11="Missing from bank","Check bank date or posting",IF(L11="Amount variance","Check invoice/payment amount","Check timing difference"))) | O11: 2000 AP | P11: Accounting Technician | Q11: No | S11: =IF(K11="Matched",0,Mapping_Rules!$B$6-B11)
A12: ERP-00009 | B12: 46052 | C12: AR | D12: West Van Fitness | E12: REF-100009 | F12: 1983.79 | G12: =IFERROR(XLOOKUP(E12,Bank_Statement!$D$4:$D$448,Bank_Statement!$G$4:$G$448,""),"") | H12: =IF(G12="","",F12-G12) | I12: =IFERROR(XLOOKUP(E12,Bank_Statement!$D$4:$D$448,Bank_Statement!$B$4:$B$448,""),"") | J12: =IF(I12="","",ABS(B12-I12)) | K12: =IF(G12="","Unmatched ERP",IF(AND(ABS(H12)<=Mapping_Rules!$B$4,ABS(J12)<=Mapping_Rules!$B$5),"Matched","Review")) | L12: =IF(K12="Matched","None",IF(G12="","Missing from bank",IF(ABS(H12)>Mapping_Rules!$B$4,"Amount variance","Date variance"))) | M12: =IF(K12="Matched","Low",IF(OR(IFERROR(ABS(H12),0)>Mapping_Rules!$B$7,IFERROR(J12,0)>Mapping_Rules!$B$8),"High","Medium")) | N12: =IF(K12="Matched","No action needed",IF(L12="Missing from bank","Check bank date or posting",IF(L12="Amount variance","Check invoice/payment amount","Check timing difference"))) | O12: 1200 AR | P12: AR Clerk | Q12: No | S12: =IF(K12="Matched",0,Mapping_Rules!$B$6-B12)
A13: ERP-00010 | B13: 46035 | C13: AP | D13: North Shore Telecom | E13: REF-100010 | F13: -5668.39 | G13: =IFERROR(XLOOKUP(E13,Bank_Statement!$D$4:$D$448,Bank_Statement!$G$4:$G$448,""),"") | H13: =IF(G13="","",F13-G13) | I13: =IFERROR(XLOOKUP(E13,Bank_Statement!$D$4:$D$448,Bank_Statement!$B$4:$B$448,""),"") | J13: =IF(I13="","",ABS(B13-I13)) | K13: =IF(G13="","Unmatched ERP",IF(AND(ABS(H13)<=Mapping_Rules!$B$4,ABS(J13)<=Mapping_Rules!$B$5),"Matched","Review")) | L13: =IF(K13="Matched","None",IF(G13="","Missing from bank",IF(ABS(H13)>Mapping_Rules!$B$4,"Amount variance","Date variance"))) | M13: =IF(K13="Matched","Low",IF(OR(IFERROR(ABS(H13),0)>Mapping_Rules!$B$7,IFERROR(J13,0)>Mapping_Rules!$B$8),"High","Medium")) | N13: =IF(K13="Matched","No action needed",IF(L13="Missing from bank","Check bank date or posting",IF(L13="Amount variance","Check invoice/payment amount","Check timing difference"))) | O13: 2000 AP | P13: AP Clerk | Q13: No | S13: =IF(K13="Matched",0,Mapping_Rules!$B$6-B13)
A14: ERP-00011 | B14: 46052 | C14: AR | D14: Coastline Foods | E14: REF-100011 | F14: 2361.75 | G14: =IFERROR(XLOOKUP(E14,Bank_Statement!$D$4:$D$448,Bank_Statement!$G$4:$G$448,""),"") | H14: =IF(G14="","",F14-G14) | I14: =IFERROR(XLOOKUP(E14,Bank_Statement!$D$4:$D$448,Bank_Statement!$B$4:$B$448,""),"") | J14: =IF(I14="","",ABS(B14-I14)) | K14: =IF(G14="","Unmatched ERP",IF(AND(ABS(H14)<=Mapping_Rules!$B$4,ABS(J14)<=Mapping_Rules!$B$5),"Matched","Review")) | L14: =IF(K14="Matched","None",IF(G14="","Missing from bank",IF(ABS(H14)>Mapping_Rules!$B$4,"Amount variance","Date variance"))) | M14: =IF(K14="Matched","Low",IF(OR(IFERROR(ABS(H14),0)>Mapping_Rules!$B$7,IFERROR(J14,0)>Mapping_Rules!$B$8),"High","Medium")) | N14: =IF(K14="Matched","No action needed",IF(L14="Missing from bank","Check bank date or posting",IF(L14="Amount variance","Check invoice/payment amount","Check timing difference"))) | O14: 1200 AR | P14: AR Clerk | Q14: No | S14: =IF(K14="Matched",0,Mapping_Rules!$B$6-B14)
A15: ERP-00012 | B15: 46035 | C15: AR | D15: Coastline Foods | E15: REF-100012 | F15: 4404.54 | G15: =IFERROR(XLOOKUP(E15,Bank_Statement!$D$4:$D$448,Bank_Statement!$G$4:$G$448,""),"") | H15: =IF(G15="","",F15-G15) | I15: =IFERROR(XLOOKUP(E15,Bank_Statement!$D$4:$D$448,Bank_Statement!$B$4:$B$448,""),"") | J15: =IF(I15="","",ABS(B15-I15)) | K15: =IF(G15="","Unmatched ERP",IF(AND(ABS(H15)<=Mapping_Rules!$B$4,ABS(J15)<=Mapping_Rules!$B$5),"Matched","Review")) | L15: =IF(K15="Matched","None",IF(G15="","Missing from bank",IF(ABS(H15)>Mapping_Rules!$B$4,"Amount variance","Date variance"))) | M15: =IF(K15="Matched","Low",IF(OR(IFERROR(ABS(H15),0)>Mapping_Rules!$B$7,IFERROR(J15,0)>Mapping_Rules!$B$8),"High","Medium")) | N15: =IF(K15="Matched","No action needed",IF(L15="Missing from bank","Check bank date or posting",IF(L15="Amount variance","Check invoice/payment amount","Check timing difference"))) | O15: 1200 AR | P15: AR Clerk | Q15: No | S15: =IF(K15="Matched",0,Mapping_Rules!$B$6-B15)
... A503: ERP-00500 | B503: 46032 | C503: GL | D503: Maple Retail Group | E503: REF-100500 | F503: -1938 | G503: =IFERROR(XLOOKUP(E503,Bank_Statement!$D$4:$D$448,Bank_Statement!$G$4:$G$448,""),"") | H503: =IF(G503="","",F503-G503) | I503: =IFERROR(XLOOKUP(E503,Bank_Statement!$D$4:$D$448,Bank_Statement!$B$4:$B$448,""),"") | J503: =IF(I503="","",ABS(B503-I503)) | K503: =IF(G503="","Unmatched ERP",IF(AND(ABS(H503)<=Mapping_Rules!$B$4,ABS(J503)<=Mapping_Rules!$B$5),"Matched","Review")) | L503: =IF(K503="Matched","None",IF(G503="","Missing from bank",IF(ABS(H503)>Mapping_Rules!$B$4,"Amount variance","Date variance"))) | M503: =IF(K503="Matched","Low",IF(OR(IFERROR(ABS(H503),0)>Mapping_Rules!$B$7,IFERROR(J503,0)>Mapping_Rules!$B$8),"High","Medium")) | N503: =IF(K503="Matched","No action needed",IF(L503="Missing from bank","Check bank date or posting",IF(L503="Amount variance","Check invoice/payment amount","Check timing difference"))) | O503: 1010 Cash | P503: Accounting Technician | Q503: No | S503: =IF(K503="Matched",0,Mapping_Rules!$B$6-B503)

Sheet Open_Invoices
A1: Open AP/AR Invoices and Aging
A3: Invoice_ID | B3: Type | C3: Customer_Vendor | D3: Invoice_Date | E3: Due_Date | F3: Original_Amount | G3: Paid_Amount | H3: Open_Amount | I3: Days_Overdue | J3: Aging_Bucket | K3: Owner | L3: Status | M3: Risk_Level | N3: Next_Action
A4: INV-00001 | B4: AP | C4: Amazon Business | D4: 46031 | E4: 46091 | F4: 9860.54 | G4: 0 | H4: =F4-G4 | I4: =MAX(0,Mapping_Rules!$B$6-E4) | J4: =IF(I4=0,"Current",IF(I4<=30,"1-30",IF(I4<=60,"31-60",IF(I4<=90,"61-90","90+")))) | K4: Finance Analyst | L4: Open | M4: =IF(L4="Closed","Closed",IF(OR(H4>=Mapping_Rules!$B$7,I4>=Mapping_Rules!$B$8),"High Risk",IF(I4>30,"Monitor","Normal"))) | N4: =IF(M4="Closed","No action",IF(M4="High Risk","Call customer/vendor and escalate",IF(M4="Monitor","Send follow-up email","Keep monitoring")))
A5: INV-00002 | B5: AR | C5: West Van Fitness | D5: 45999 | E5: 46029 | F5: 7050.81 | G5: 2876.1 | H5: =F5-G5 | I5: =MAX(0,Mapping_Rules!$B$6-E5) | J5: =IF(I5=0,"Current",IF(I5<=30,"1-30",IF(I5<=60,"31-60",IF(I5<=90,"61-90","90+")))) | K5: AP Clerk | L5: Part Paid | M5: =IF(L5="Closed","Closed",IF(OR(H5>=Mapping_Rules!$B$7,I5>=Mapping_Rules!$B$8),"High Risk",IF(I5>30,"Monitor","Normal"))) | N5: =IF(M5="Closed","No action",IF(M5="High Risk","Call customer/vendor and escalate",IF(M5="Monitor","Send follow-up email","Keep monitoring")))
A6: INV-00003 | B6: AR | C6: West Van Fitness | D6: 46049 | E6: 46079 | F6: 11394.51 | G6: 0 | H6: =F6-G6 | I6: =MAX(0,Mapping_Rules!$B$6-E6) | J6: =IF(I6=0,"Current",IF(I6<=30,"1-30",IF(I6<=60,"31-60",IF(I6<=90,"61-90","90+")))) | K6: AR Clerk | L6: Open | M6: =IF(L6="Closed","Closed",IF(OR(H6>=Mapping_Rules!$B$7,I6>=Mapping_Rules!$B$8),"High Risk",IF(I6>30,"Monitor","Normal"))) | N6: =IF(M6="Closed","No action",IF(M6="High Risk","Call customer/vendor and escalate",IF(M6="Monitor","Send follow-up email","Keep monitoring")))
A7: INV-00004 | B7: AR | C7: West Van Fitness | D7: 46034 | E7: 46064 | F7: 11078.41 | G7: 0 | H7: =F7-G7 | I7: =MAX(0,Mapping_Rules!$B$6-E7) | J7: =IF(I7=0,"Current",IF(I7<=30,"1-30",IF(I7<=60,"31-60",IF(I7<=90,"61-90","90+")))) | K7: Accounting Technician | L7: Open | M7: =IF(L7="Closed","Closed",IF(OR(H7>=Mapping_Rules!$B$7,I7>=Mapping_Rules!$B$8),"High Risk",IF(I7>30,"Monitor","Normal"))) | N7: =IF(M7="Closed","No action",IF(M7="High Risk","Call customer/vendor and escalate",IF(M7="Monitor","Send follow-up email","Keep monitoring")))
A8: INV-00005 | B8: AR | C8: Coastline Foods | D8: 46024 | E8: 46054 | F8: 1083.49 | G8: 0 | H8: =F8-G8 | I8: =MAX(0,Mapping_Rules!$B$6-E8) | J8: =IF(I8=0,"Current",IF(I8<=30,"1-30",IF(I8<=60,"31-60",IF(I8<=90,"61-90","90+")))) | K8: AP Clerk | L8: Open | M8: =IF(L8="Closed","Closed",IF(OR(H8>=Mapping_Rules!$B$7,I8>=Mapping_Rules!$B$8),"High Risk",IF(I8>30,"Monitor","Normal"))) | N8: =IF(M8="Closed","No action",IF(M8="High Risk","Call customer/vendor and escalate",IF(M8="Monitor","Send follow-up email","Keep monitoring")))
A9: INV-00006 | B9: AR | C9: West Van Fitness | D9: 46008 | E9: 46068 | F9: 7124.66 | G9: 0 | H9: =F9-G9 | I9: =MAX(0,Mapping_Rules!$B$6-E9) | J9: =IF(I9=0,"Current",IF(I9<=30,"1-30",IF(I9<=60,"31-60",IF(I9<=90,"61-90","90+")))) | K9: AP Clerk | L9: Open | M9: =IF(L9="Closed","Closed",IF(OR(H9>=Mapping_Rules!$B$7,I9>=Mapping_Rules!$B$8),"High Risk",IF(I9>30,"Monitor","Normal"))) | N9: =IF(M9="Closed","No action",IF(M9="High Risk","Call customer/vendor and escalate",IF(M9="Monitor","Send follow-up email","Keep monitoring")))
A10: INV-00007 | B10: AR | C10: Harbour Design Co. | D10: 46003 | E10: 46018 | F10: 10600.48 | G10: 7306.6 | H10: =F10-G10 | I10: =MAX(0,Mapping_Rules!$B$6-E10) | J10: =IF(I10=0,"Current",IF(I10<=30,"1-30",IF(I10<=60,"31-60",IF(I10<=90,"61-90","90+")))) | K10: Accounting Technician | L10: Part Paid | M10: =IF(L10="Closed","Closed",IF(OR(H10>=Mapping_Rules!$B$7,I10>=Mapping_Rules!$B$8),"High Risk",IF(I10>30,"Monitor","Normal"))) | N10: =IF(M10="Closed","No action",IF(M10="High Risk","Call customer/vendor and escalate",IF(M10="Monitor","Send follow-up email","Keep monitoring")))
A11: INV-00008 | B11: AR | C11: Granville Medical | D11: 46045 | E11: 46105 | F11: 5574.66 | G11: 3863.55 | H11: =F11-G11 | I11: =MAX(0,Mapping_Rules!$B$6-E11) | J11: =IF(I11=0,"Current",IF(I11<=30,"1-30",IF(I11<=60,"31-60",IF(I11<=90,"61-90","90+")))) | K11: Accounting Technician | L11: Part Paid | M11: =IF(L11="Closed","Closed",IF(OR(H11>=Mapping_Rules!$B$7,I11>=Mapping_Rules!$B$8),"High Risk",IF(I11>30,"Monitor","Normal"))) | N11: =IF(M11="Closed","No action",IF(M11="High Risk","Call customer/vendor and escalate",IF(M11="Monitor","Send follow-up email","Keep monitoring")))
A12: INV-00009 | B12: AP | C12: North Shore Telecom | D12: 46028 | E12: 46088 | F12: 5390.54 | G12: 0 | H12: =F12-G12 | I12: =MAX(0,Mapping_Rules!$B$6-E12) | J12: =IF(I12=0,"Current",IF(I12<=30,"1-30",IF(I12<=60,"31-60",IF(I12<=90,"61-90","90+")))) | K12: Finance Analyst | L12: Promise to Pay | M12: =IF(L12="Closed","Closed",IF(OR(H12>=Mapping_Rules!$B$7,I12>=Mapping_Rules!$B$8),"High Risk",IF(I12>30,"Monitor","Normal"))) | N12: =IF(M12="Closed","No action",IF(M12="High Risk","Call customer/vendor and escalate",IF(M12="Monitor","Send follow-up email","Keep monitoring")))
A13: INV-00010 | B13: AP | C13: Amazon Business | D13: 45962 | E13: 45992 | F13: 6682.5 | G13: 0 | H13: =F13-G13 | I13: =MAX(0,Mapping_Rules!$B$6-E13) | J13: =IF(I13=0,"Current",IF(I13<=30,"1-30",IF(I13<=60,"31-60",IF(I13<=90,"61-90","90+")))) | K13: Accounting Technician | L13: Open | M13: =IF(L13="Closed","Closed",IF(OR(H13>=Mapping_Rules!$B$7,I13>=Mapping_Rules!$B$8),"High Risk",IF(I13>30,"Monitor","Normal"))) | N13: =IF(M13="Closed","No action",IF(M13="High Risk","Call customer/vendor and escalate",IF(M13="Monitor","Send follow-up email","Keep monitoring")))
A14: INV-00011 | B14: AR | C14: Coastline Foods | D14: 45985 | E14: 46015 | F14: 5529.01 | G14: 0 | H14: =F14-G14 | I14: =MAX(0,Mapping_Rules!$B$6-E14) | J14: =IF(I14=0,"Current",IF(I14<=30,"1-30",IF(I14<=60,"31-60",IF(I14<=90,"61-90","90+")))) | K14: AP Clerk | L14: Disputed | M14: =IF(L14="Closed","Closed",IF(OR(H14>=Mapping_Rules!$B$7,I14>=Mapping_Rules!$B$8),"High Risk",IF(I14>30,"Monitor","Normal"))) | N14: =IF(M14="Closed","No action",IF(M14="High Risk","Call customer/vendor and escalate",IF(M14="Monitor","Send follow-up email","Keep monitoring")))
A15: INV-00012 | B15: AR | C15: Granville Medical | D15: 46004 | E15: 46019 | F15: 7300.52 | G15: 0 | H15: =F15-G15 | I15: =MAX(0,Mapping_Rules!$B$6-E15) | J15: =IF(I15=0,"Current",IF(I15<=30,"1-30",IF(I15<=60,"31-60",IF(I15<=90,"61-90","90+")))) | K15: AR Clerk | L15: Open | M15: =IF(L15="Closed","Closed",IF(OR(H15>=Mapping_Rules!$B$7,I15>=Mapping_Rules!$B$8),"High Risk",IF(I15>30,"Monitor","Normal"))) | N15: =IF(M15="Closed","No action",IF(M15="High Risk","Call customer/vendor and escalate",IF(M15="Monitor","Send follow-up email","Keep monitoring")))
... A223: INV-00220 | B223: AP | C223: BC Hydro | D223: 46031 | E223: 46076 | F223: 646.91 | G223: 0 | H223: =F223-G223 | I223: =MAX(0,Mapping_Rules!$B$6-E223) | J223: =IF(I223=0,"Current",IF(I223<=30,"1-30",IF(I223<=60,"31-60",IF(I223<=90,"61-90","90+")))) | K223: Finance Analyst | L223: Open | M223: =IF(L223="Closed","Closed",IF(OR(H223>=Mapping_Rules!$B$7,I223>=Mapping_Rules!$B$8),"High Risk",IF(I223>30,"Monitor","Normal"))) | N223: =IF(M223="Closed","No action",IF(M223="High Risk","Call customer/vendor and escalate",IF(M223="Monitor","Send follow-up email","Keep monitoring")))

Sheet Analysis_Model
A1: Analysis Model - Formula Summary
A3: Metric | B3: Value | C3: Formula meaning | E3: Reconciliation Status | F3: Count | H3: Aging Bucket | I3: Open Amount | K3: Module | L3: Absolute Amount | N3: Risk Level | O3: Count
A4: Total ERP transactions | B4: =COUNTA(ERP_Transactions!$A$4:$A$503) | C4: Count all ERP transaction rows | E4: Matched | F4: =COUNTIF(Reconciliation!$K$4:$K$503,E4) | H4: Current | I4: =SUMIF(Open_Invoices!$J$4:$J$223,H4,Open_Invoices!$H$4:$H$223) | K4: AP | L4: =SUMIFS(ERP_Transactions!$H$4:$H$503,ERP_Transactions!$D$4:$D$503,K4)+SUMIFS(ERP_Transactions!$I$4:$I$503,ERP_Transactions!$D$4:$D$503,K4) | N4: Closed | O4: =COUNTIF(Open_Invoices!$M$4:$M$223,N4)
A5: Total bank transactions | B5: =COUNTA(Bank_Statement!$A$4:$A$448) | C5: Count all bank statement rows | E5: Review | F5: =COUNTIF(Reconciliation!$K$4:$K$503,E5) | H5: 1-30 | I5: =SUMIF(Open_Invoices!$J$4:$J$223,H5,Open_Invoices!$H$4:$H$223) | K5: AR | L5: =SUMIFS(ERP_Transactions!$H$4:$H$503,ERP_Transactions!$D$4:$D$503,K5)+SUMIFS(ERP_Transactions!$I$4:$I$503,ERP_Transactions!$D$4:$D$503,K5) | N5: High Risk | O5: =COUNTIF(Open_Invoices!$M$4:$M$223,N5)
A6: Matched transactions | B6: =COUNTIF(Reconciliation!$K$4:$K$503,"Matched") | C6: Count status = Matched | E6: Unmatched ERP | F6: =COUNTIF(Reconciliation!$K$4:$K$503,E6) | H6: 31-60 | I6: =SUMIF(Open_Invoices!$J$4:$J$223,H6,Open_Invoices!$H$4:$H$223) | K6: GL | L6: =SUMIFS(ERP_Transactions!$H$4:$H$503,ERP_Transactions!$D$4:$D$503,K6)+SUMIFS(ERP_Transactions!$I$4:$I$503,ERP_Transactions!$D$4:$D$503,K6) | N6: Monitor | O6: =COUNTIF(Open_Invoices!$M$4:$M$223,N6)
A7: Review transactions | B7: =COUNTIF(Reconciliation!$K$4:$K$503,"Review") | C7: Count status = Review | H7: 61-90 | I7: =SUMIF(Open_Invoices!$J$4:$J$223,H7,Open_Invoices!$H$4:$H$223) | K7: Payroll | L7: =SUMIFS(ERP_Transactions!$H$4:$H$503,ERP_Transactions!$D$4:$D$503,K7)+SUMIFS(ERP_Transactions!$I$4:$I$503,ERP_Transactions!$D$4:$D$503,K7) | N7: Normal | O7: =COUNTIF(Open_Invoices!$M$4:$M$223,N7)
A8: Unmatched ERP transactions | B8: =COUNTIF(Reconciliation!$K$4:$K$503,"Unmatched ERP") | C8: Count status = Unmatched ERP | H8: 90+ | I8: =SUMIF(Open_Invoices!$J$4:$J$223,H8,Open_Invoices!$H$4:$H$223) | K8: Bank Fees | L8: =SUMIFS(ERP_Transactions!$H$4:$H$503,ERP_Transactions!$D$4:$D$503,K8)+SUMIFS(ERP_Transactions!$I$4:$I$503,ERP_Transactions!$D$4:$D$503,K8)
A9: Match rate | B9: =IFERROR(B6/B4,0) | C9: Matched / Total ERP transactions
A10: Bank-only items | B10: =COUNTIF(Bank_Statement!$H$4:$H$448,"Needs ERP Review") | C10: Bank rows not found in ERP
A11: Open invoice amount | B11: =SUM(Open_Invoices!$H$4:$H$223) | C11: Sum open invoice balance
A12: High-risk invoices | B12: =COUNTIF(Open_Invoices!$M$4:$M$223,"High Risk") | C12: Count high-risk invoices
A13: Total exceptions | B13: =COUNTA(Exception_Log!$A$4:$A$83) | C13: Count exception log rows
A16: Optional Power Pivot / DAX measures for portfolio explanation
A17: Measure Name | B17: DAX Formula | C17: Simple meaning
A18: Total Open Amount | B18: Total Open Amount := SUM(Open_Invoices[Open_Amount]) | C18: Total money still open
A19: Matched Count | B19: Matched Count := CALCULATE(COUNTROWS(Reconciliation), Reconciliation[Reconciliation_Status] = "Matched") | C19: How many items matched
A20: Match Rate | B20: Match Rate := DIVIDE([Matched Count], COUNTROWS(Reconciliation)) | C20: Percent of ERP items matched
A21: High Risk Invoice Count | B21: High Risk Invoice Count := CALCULATE(COUNTROWS(Open_Invoices), Open_Invoices[Risk_Level] = "High Risk") | C21: How many invoices need quick action

Sheet Exception_Log
A1: Exception Log - Items That Need Review
A3: Exception_ID | B3: Source | C3: Reference_No | D3: Date | E3: Name | F3: Amount | G3: Exception_Type | H3: Priority | I3: Owner | J3: Suggested_Action
A4: EX-0215 | B4: Open Invoice | C4: INV-00047 | D4: 45977 | E4: Amazon Business | F4: 12742.96 | G4: Invoice risk | H4: High | I4: AP Clerk | J4: Escalate and follow up
A5: EX-0285 | B5: Open Invoice | C5: INV-00177 | D5: 45977 | E5: Vancouver Courier | F5: 10334.66 | G5: Invoice risk | H5: High | I5: AP Clerk | J5: Escalate and follow up
A6: EX-0232 | B6: Open Invoice | C6: INV-00074 | D6: 45978 | E6: Raincity Tech | F6: 7921.25 | G6: Invoice risk | H6: High | I6: AR Clerk | J6: Escalate and follow up
A7: EX-0243 | B7: Open Invoice | C7: INV-00086 | D7: 45978 | E7: Vancouver Courier | F7: 14622.79 | G7: Invoice risk | H7: High | I7: AP Clerk | J7: Escalate and follow up
A8: EX-0295 | B8: Open Invoice | C8: INV-00192 | D8: 45978 | E8: Pacific Office Supplies | F8: 3217.67 | G8: Invoice risk | H8: High | I8: AP Clerk | J8: Escalate and follow up
A9: EX-0254 | B9: Open Invoice | C9: INV-00106 | D9: 45982 | E9: Amazon Business | F9: 12541.68 | G9: Invoice risk | H9: High | I9: AP Clerk | J9: Escalate and follow up
A10: EX-0297 | B10: Open Invoice | C10: INV-00195 | D10: 45983 | E10: Granville Medical | F10: 6483.02 | G10: Invoice risk | H10: High | I10: AR Clerk | J10: Escalate and follow up
A11: EX-0270 | B11: Open Invoice | C11: INV-00144 | D11: 45985 | E11: Raincity Tech | F11: 2884.41 | G11: Invoice risk | H11: High | I11: AR Clerk | J11: Escalate and follow up
A12: EX-0195 | B12: Open Invoice | C12: INV-00010 | D12: 45992 | E12: Amazon Business | F12: 6682.5 | G12: Invoice risk | H12: High | I12: AP Clerk | J12: Escalate and follow up
A13: EX-0220 | B13: Open Invoice | C13: INV-00057 | D13: 45993 | E13: Vancouver Courier | F13: 6409.58 | G13: Invoice risk | H13: High | I13: AP Clerk | J13: Escalate and follow up
A14: EX-0280 | B14: Open Invoice | C14: INV-00166 | D14: 45995 | E14: Coastline Foods | F14: 9851.16 | G14: Invoice risk | H14: High | I14: AR Clerk | J14: Escalate and follow up
A15: EX-0244 | B15: Open Invoice | C15: INV-00087 | D15: 45996 | E15: North Shore Telecom | F15: 6993.39 | G15: Invoice risk | H15: High | I15: AP Clerk | J15: Escalate and follow up
... A83: EX-0010 | B83: Reconciliation | C83: REF-100043 | D83: 46051 | E83: Payroll Batch | F83: -16620.64 | G83: Missing from bank | H83: High | I83: Accounting Technician | J83: Check bank statement or payment date

Sheet Power_Query_Blueprint
A1: Power Query Blueprint - How to Automate This Project
A3: Step | B3: Query Name | C3: Source | D3: Action | E3: Output | F3: Simple explanation
A4: 1 | B4: Load_ERP_Transactions | C4: ERP export CSV | D4: Change data types, trim text, remove blank rows | E4: ERP_Transactions | F4: Clean ERP data before analysis
A5: 2 | B5: Load_Bank_Statement | C5: Bank CSV | D5: Change date and amount types, clean reference number | E5: Bank_Statement | F5: Prepare bank data for matching
A6: 3 | B6: Merge_ERP_to_Bank | C6: ERP + Bank | D6: Left join by Reference_No | E6: Reconciliation | F6: Find bank match for each ERP item
A7: 4 | B7: Find_Bank_Only | C7: Bank + ERP | D7: Anti join where bank reference is not in ERP | E7: Exception_Log | F7: Find bank items missing in ERP
A8: 5 | B8: Load_Open_Invoices | C8: AP/AR aging export | D8: Calculate open amount and aging bucket | E8: Open_Invoices | F8: Find old or high-risk invoices
A9: 6 | B9: Build_Model | C9: All clean tables | D9: Load to Power Pivot data model | E9: Analysis_Model | F9: Create reusable reporting model
A10: 7 | B10: Refresh_Dashboard | C10: Data model | D10: Refresh all queries and formulas | E10: Dashboard | F10: Update KPIs for month-end close

Sheet Dashboard
A1: Month-End Close Dashboard
A2: Purpose: Show key month-end close risks in one simple view. Start here, then go to Reconciliation or Open_Invoices to fix details.
A4: ="Match Rate: "&TEXT(Analysis_Model!B9,"0.0%") | C4: ="Unmatched ERP: "&TEXT(Analysis_Model!B8,"#,##0") | E4: ="Bank-only Items: "&TEXT(Analysis_Model!B10,"#,##0")
A7: ="Open Invoice Amount: "&TEXT(Analysis_Model!B11,"$#,##0") | C7: ="High-risk Invoices: "&TEXT(Analysis_Model!B12,"#,##0") | E7: ="Total Exceptions: "&TEXT(Analysis_Model!B13,"#,##0")
A11: Reconciliation Status | B11: Count | D11: Aging Bucket | E11: Open Amount
A12: Matched | B12: =Analysis_Model!F4 | D12: =Analysis_Model!H4 | E12: =Analysis_Model!I4
A13: Review | B13: =Analysis_Model!F5 | D13: =Analysis_Model!H5 | E13: =Analysis_Model!I5
A14: Unmatched ERP | B14: =Analysis_Model!F6 | D14: =Analysis_Model!H6 | E14: =Analysis_Model!I6
D15: =Analysis_Model!H7 | E15: =Analysis_Model!I7
D16: =Analysis_Model!H8 | E16: =Analysis_Model!I8
A18: How to read this dashboard
A19: 1 | B19: If match rate is low, check the Reconciliation sheet.
A20: 2 | B20: If there are bank-only items, check if ERP entries are missing.
A21: 3 | B21: If high-risk invoices are high, review Open_Invoices and contact the owner.
A22: 4 | B22: Use Exception_Log to see the most urgent items first.
A30: Module | B30: Absolute Amount | D30: Risk Level | E30: Count
A31: =Analysis_Model!K4 | B31: =Analysis_Model!L4 | D31: =Analysis_Model!N4 | E31: =Analysis_Model!O4
A32: =Analysis_Model!K5 | B32: =Analysis_Model!L5 | D32: =Analysis_Model!N5 | E32: =Analysis_Model!O5
A33: =Analysis_Model!K6 | B33: =Analysis_Model!L6 | D33: =Analysis_Model!N6 | E33: =Analysis_Model!O6
A34: =Analysis_Model!K7 | B34: =Analysis_Model!L7 | D34: =Analysis_Model!N7 | E34: =Analysis_Model!O7
A35: =Analysis_Model!K8 | B35: =Analysis_Model!L8
