Workbook

Sheet Project Overview
A1: UrbanBite Café & Bakery Group
A2: Business Case & Excel Project Overview
A4: Project Type | B4: Advanced Excel Sales Analytics Dashboard | E4: KPI Definitions
A5: Reporting Period | B5: Fiscal Year 2025 | E5: KPI | F5: Meaning | G5: Why It Matters
A6: Prepared For | B6: Executive Management & Regional Operations Team | E6: Revenue | F6: Total sales generated by region. | G6: Shows business size and demand.
A7: Prepared By | B7: Alireza Kanzagh | E7: Gross Profit | F7: Revenue minus cost. | G7: Shows how much money remains before expenses.
A8: Workbook Version | B8: Version 1.0 | E8: Gross Margin | F8: Gross Profit divided by Revenue. | G8: Measures profitability efficiency.
E9: Variance to Target | F9: Actual revenue minus target revenue. | G9: Shows if a region met expectations.
A10: Company Overview
A11: UrbanBite Café & Bakery Group is a fictional Canadian food service and bakery distribution company. The business operates regional bakery cafés and supplies packaged baked goods to local retailers, coffee shops, and food-service partners across major Canadian cities. Management uses this workbook to review quarterly sales performance, compare regional profitability, and identify areas that need improvement.
A16: Project Objective
A17: This Excel project is designed to show how a business analyst can transform regional sales data into a clear management report.
A18: The workbook helps users track revenue, cost, gross profit, gross margin, sales targets, variance, and regional ranking.
A19: It also includes dashboard visuals and KPI cards so decision makers can quickly understand business performance.
A21: Main business question:
A22: Which regions are generating the strongest revenue and profit, and which regions need management attention?
A24: Workbook Structure
A25: Worksheet | B25: Purpose | C25: User
A26: Project Overview | B26: Explains the fictional business, project goal, and workbook structure. | C26: Reviewer / Instructor / Employer
A27: Dashboard | B27: Shows executive KPIs, charts, and regional performance summary. | C27: Management
A28: Sales_Data | B28: Contains detailed monthly and quarterly sales records by region. | C28: Analyst
A29: Regional_Summary | B29: Summarizes revenue, cost, profit, margin, targets, variance, and ranking. | C29: Analyst / Manager
A30: Lookups | B30: Stores support lists used for categories and business assumptions. | C30: Workbook Owner

Sheet Sales_Data
A1: Month | B1: Region | C1: Category | D1: Units Sold | E1: Revenue | F1: Cost | G1: Gross Profit | H1: Target Revenue | I1: Variance | J1: Status
A2: 45658 | B2: Toronto | C2: Artisan Bread | D2: 3112 | E2: 23347 | F2: 11081 | G2: =E2-F2 -> 12266 | H2: 23168 | I2: =E2-H2 -> 179 | J2: =IF(I2>=0,"Above Target","Below Target") -> Above Target
A3: 45658 | B3: Toronto | C3: Pastries | D3: 4281 | E3: 22477 | F3: 9524 | G3: =E3-F3 -> 12953 | H3: 23808 | I3: =E3-H3 -> -1331 | J3: =IF(I3>=0,"Above Target","Below Target") -> Below Target
A4: 45658 | B4: Toronto | C4: Cakes & Desserts | D4: 1088 | E4: 26125 | F4: 13272 | G4: =E4-F4 -> 12853 | H4: 25419 | I4: =E4-H4 -> 706 | J4: =IF(I4>=0,"Above Target","Below Target") -> Above Target
A5: 45658 | B5: Toronto | C5: Coffee & Beverages | D5: 3084 | E5: 14650 | F5: 4982 | G5: =E5-F5 -> 9668 | H5: 14249 | I5: =E5-H5 -> 401 | J5: =IF(I5>=0,"Above Target","Below Target") -> Above Target
A6: 45658 | B6: Montreal | C6: Artisan Bread | D6: 2986 | E6: 22401 | F6: 10777 | G6: =E6-F6 -> 11624 | H6: 22223 | I6: =E6-H6 -> 178 | J6: =IF(I6>=0,"Above Target","Below Target") -> Above Target
A7: 45658 | B7: Montreal | C7: Pastries | D7: 3622 | E7: 19019 | F7: 8112 | G7: =E7-F7 -> 10907 | H7: 18461 | I7: =E7-H7 -> 558 | J7: =IF(I7>=0,"Above Target","Below Target") -> Above Target
A8: 45658 | B8: Montreal | C8: Cakes & Desserts | D8: 1058 | E8: 25405 | F8: 13085 | G8: =E8-F8 -> 12320 | H8: 25507 | I8: =E8-H8 -> -102 | J8: =IF(I8>=0,"Above Target","Below Target") -> Below Target
A9: 45658 | B9: Montreal | C9: Coffee & Beverages | D9: 2642 | E9: 12550 | F9: 4365 | G9: =E9-F9 -> 8185 | H9: 12596 | I9: =E9-H9 -> -46 | J9: =IF(I9>=0,"Above Target","Below Target") -> Below Target
A10: 45658 | B10: Ottawa | C10: Artisan Bread | D10: 1795 | E10: 13464 | F10: 6575 | G10: =E10-F10 -> 6889 | H10: 13873 | I10: =E10-H10 -> -409 | J10: =IF(I10>=0,"Above Target","Below Target") -> Below Target
A11: 45658 | B11: Ottawa | C11: Pastries | D11: 2465 | E11: 12943 | F11: 5499 | G11: =E11-F11 -> 7444 | H11: 13249 | I11: =E11-H11 -> -306 | J11: =IF(I11>=0,"Above Target","Below Target") -> Below Target
A12: 45658 | B12: Ottawa | C12: Cakes & Desserts | D12: 714 | E12: 17141 | F12: 8689 | G12: =E12-F12 -> 8452 | H12: 17573 | I12: =E12-H12 -> -432 | J12: =IF(I12>=0,"Above Target","Below Target") -> Below Target
A13: 45658 | B13: Ottawa | C13: Coffee & Beverages | D13: 1936 | E13: 9199 | F13: 3146 | G13: =E13-F13 -> 6053 | H13: 9716 | I13: =E13-H13 -> -517 | J13: =IF(I13>=0,"Above Target","Below Target") -> Below Target
... A241: 45992 | B241: Vancouver | C241: Coffee & Beverages | D241: 3381 | E241: 16061 | F241: 5450 | G241: =E241-F241 -> 10611 | H241: 15768 | I241: =E241-H241 -> 293 | J241: =IF(I241>=0,"Above Target","Below Target") -> Above Target

Sheet Lookups
A1: Setting | B1: Value | D1: Regions | F1: Categories
A2: Company Name | B2: UrbanBite Café & Bakery Group | D2: Toronto | F2: Artisan Bread
A3: Fiscal Year | B3: 2025 | D3: Montreal | F3: Pastries
A4: Currency | B4: CAD | D4: Ottawa | F4: Cakes & Desserts
A5: Prepared For | B5: Portfolio Demo | D5: Calgary | F5: Coffee & Beverages
A6: Data Type | B6: Fictional / anonymized | D6: Vancouver
A7: Last Updated | B7: 46180

Sheet Regional_Summary
A1: UrbanBite Café & Bakery Group - Regional Performance Summary
A3: Region | B3: Total Revenue | C3: Total Cost | D3: Gross Profit | E3: Gross Margin | F3: Target Revenue | G3: Variance | H3: Rank
A4: Toronto | B4: =SUMIFS(Sales_Data!$E:$E,Sales_Data!$B:$B,A4) -> 1176333 | C4: =SUMIFS(Sales_Data!$F:$F,Sales_Data!$B:$B,A4) -> 529865 | D4: =B4-C4 -> 646468 | E4: =D4/B4 -> 0.54956207 | F4: =SUMIFS(Sales_Data!$H:$H,Sales_Data!$B:$B,A4) -> 1198931 | G4: =B4-F4 -> -22598 | H4: =RANK(B4,$B$4:$B$8,0) -> 1
A5: Montreal | B5: =SUMIFS(Sales_Data!$E:$E,Sales_Data!$B:$B,A5) -> 1064548 | C5: =SUMIFS(Sales_Data!$F:$F,Sales_Data!$B:$B,A5) -> 482091 | D5: =B5-C5 -> 582457 | E5: =D5/B5 -> 0.54714019 | F5: =SUMIFS(Sales_Data!$H:$H,Sales_Data!$B:$B,A5) -> 1083891 | G5: =B5-F5 -> -19343 | H5: =RANK(B5,$B$4:$B$8,0) -> 2
A6: Ottawa | B6: =SUMIFS(Sales_Data!$E:$E,Sales_Data!$B:$B,A6) -> 711796 | C6: =SUMIFS(Sales_Data!$F:$F,Sales_Data!$B:$B,A6) -> 322166 | D6: =B6-C6 -> 389630 | E6: =D6/B6 -> 0.54738998 | F6: =SUMIFS(Sales_Data!$H:$H,Sales_Data!$B:$B,A6) -> 717609 | G6: =B6-F6 -> -5813 | H6: =RANK(B6,$B$4:$B$8,0) -> 5
A7: Calgary | B7: =SUMIFS(Sales_Data!$E:$E,Sales_Data!$B:$B,A7) -> 875284 | C7: =SUMIFS(Sales_Data!$F:$F,Sales_Data!$B:$B,A7) -> 395627 | D7: =B7-C7 -> 479657 | E7: =D7/B7 -> 0.54800156 | F7: =SUMIFS(Sales_Data!$H:$H,Sales_Data!$B:$B,A7) -> 890828 | G7: =B7-F7 -> -15544 | H7: =RANK(B7,$B$4:$B$8,0) -> 4
A8: Vancouver | B8: =SUMIFS(Sales_Data!$E:$E,Sales_Data!$B:$B,A8) -> 929360 | C8: =SUMIFS(Sales_Data!$F:$F,Sales_Data!$B:$B,A8) -> 419834 | D8: =B8-C8 -> 509526 | E8: =D8/B8 -> 0.54825471 | F8: =SUMIFS(Sales_Data!$H:$H,Sales_Data!$B:$B,A8) -> 949728 | G8: =B8-F8 -> -20368 | H8: =RANK(B8,$B$4:$B$8,0) -> 3

Sheet Dashboard
A1: UrbanBite Café & Bakery Group - Executive Dashboard
A3: Total Revenue | B3: Total Cost | C3: Gross Profit | D3: Avg Gross Margin | E3: Best Region | F3: Needs Attention | G3: Regions | H3: Reporting Year
A4: =SUM(Regional_Summary!B4:B8) -> 4757321 | B4: =SUM(Regional_Summary!C4:C8) -> 2149583 | C4: =SUM(Regional_Summary!D4:D8) -> 2607738 | D4: =AVERAGE(Regional_Summary!E4:E8) -> 0.5480697 | E4: =INDEX(Regional_Summary!A4:A8,MATCH(MAX(Regional_Summary!B4:B8),Regional_Summary!B4:B8,0)) -> Toronto | F4: =INDEX(Regional_Summary!A4:A8,MATCH(MIN(Regional_Summary!G4:G8),Regional_Summary!G4:G8,0)) -> Toronto | G4: =COUNTA(Regional_Summary!A4:A8) -> 5 | H4: =2025 -> 2025
A7: Region | B7: Revenue | C7: Cost | D7: Gross Profit | E7: Margin | F7: Target | G7: Variance | H7: Rank
A8: =Regional_Summary!A4 -> Toronto | B8: =Regional_Summary!B4 -> 1176333 | C8: =Regional_Summary!C4 -> 529865 | D8: =Regional_Summary!D4 -> 646468 | E8: =Regional_Summary!E4 -> 0.54956207 | F8: =Regional_Summary!F4 -> 1198931 | G8: =Regional_Summary!G4 -> -22598 | H8: =Regional_Summary!H4 -> 1
A9: =Regional_Summary!A5 -> Montreal | B9: =Regional_Summary!B5 -> 1064548 | C9: =Regional_Summary!C5 -> 482091 | D9: =Regional_Summary!D5 -> 582457 | E9: =Regional_Summary!E5 -> 0.54714019 | F9: =Regional_Summary!F5 -> 1083891 | G9: =Regional_Summary!G5 -> -19343 | H9: =Regional_Summary!H5 -> 2
A10: =Regional_Summary!A6 -> Ottawa | B10: =Regional_Summary!B6 -> 711796 | C10: =Regional_Summary!C6 -> 322166 | D10: =Regional_Summary!D6 -> 389630 | E10: =Regional_Summary!E6 -> 0.54738998 | F10: =Regional_Summary!F6 -> 717609 | G10: =Regional_Summary!G6 -> -5813 | H10: =Regional_Summary!H6 -> 5
A11: =Regional_Summary!A7 -> Calgary | B11: =Regional_Summary!B7 -> 875284 | C11: =Regional_Summary!C7 -> 395627 | D11: =Regional_Summary!D7 -> 479657 | E11: =Regional_Summary!E7 -> 0.54800156 | F11: =Regional_Summary!F7 -> 890828 | G11: =Regional_Summary!G7 -> -15544 | H11: =Regional_Summary!H7 -> 4
A12: =Regional_Summary!A8 -> Vancouver | B12: =Regional_Summary!B8 -> 929360 | C12: =Regional_Summary!C8 -> 419834 | D12: =Regional_Summary!D8 -> 509526 | E12: =Regional_Summary!E8 -> 0.54825471 | F12: =Regional_Summary!F8 -> 949728 | G12: =Regional_Summary!G8 -> -20368 | H12: =Regional_Summary!H8 -> 3
